{
    "gunitaksharas": [
        {
            "id": 1,
            "gunitakshara": "ಖ",
            "isAvailable": true,
            "similarForms": [],
            "differentForms": []
        },
        {
            "id": 2,
            "gunitakshara": "ಖಾ",
            "isAvailable": true,
            "similarForms": [],
            "differentForms": []
        },
        {
            "id": 3,
            "gunitakshara": "ಖಿ",
            "isAvailable": true,
            "similarForms": [],
            "differentForms": []
        },
        {
            "id": 4,
            "gunitakshara": "ಖೀ",
            "isAvailable": true,
            "similarForms": [],
            "differentForms": []
        },
        {
            "id": 5,
            "gunitakshara": "ಖು",
            "isAvailable": true,
            "similarForms": [],
            "differentForms": []
        },
        {
            "id": 6,
            "gunitakshara": "ಖೂ",
            "isAvailable": true,
            "similarForms": [],
            "differentForms": []
        },
        {
            "id": 7,
            "gunitakshara": "ಖೃ",
            "isAvailable": true,
            "similarForms": [],
            "differentForms": []
        },
        {
            "id": 8,
            "gunitakshara": "ಖೆ",
            "isAvailable": true,
            "similarForms": [],
            "differentForms": []
        },
        {
            "id": 9,
            "gunitakshara": "ಖೇ",
            "isAvailable": true,
            "similarForms": [],
            "differentForms": []
        },
        {
            "id": 10,
            "gunitakshara": "ಖೈ",
            "isAvailable": true,
            "similarForms": [],
            "differentForms": []
        },
        {
            "id": 11,
            "gunitakshara": "ಖೊ",
            "isAvailable": true,
            "similarForms": [],
            "differentForms": []
        },
        {
            "id": 12,
            "gunitakshara": "ಖೋ",
            "isAvailable": true,
            "similarForms": [],
            "differentForms": []
        },
        {
            "id": 13,
            "gunitakshara": "ಖೌ",
            "isAvailable": true,
            "similarForms": [],
            "differentForms": []
        },
        {
            "id": 14,
            "gunitakshara": "ಖಂ",
            "isAvailable": true,
            "similarForms": [],
            "differentForms": []
        },
        {
            "id": 15,
            "gunitakshara": "ಖಃ",
            "isAvailable": true,
            "similarForms": [],
            "differentForms": []
        }
    ]
}